nonebot_plugin_note/__init__.py
nonebot_plugin_note-0.2.3.dist-info/METADATA
nonebot_plugin_note-0.2.3.dist-info/WHEEL
nonebot_plugin_note-0.2.3.dist-info/top_level.txt
nonebot_plugin_note-0.2.3.dist-info/RECORD
