Metadata-Version: 2.1
Name: nonebot-plugin-note
Version: 0.2.3
Requires-Dist: pillow
Requires-Dist: nonebot2
Requires-Dist: nonebot-plugin-apscheduler
Requires-Dist: nonebot-adapter-onebot
